colorred_py/__init__.py
colorred_py/colorize.py
colorred_py-1.0.1.dist-info/LICENSE
colorred_py-1.0.1.dist-info/METADATA
colorred_py-1.0.1.dist-info/WHEEL
colorred_py-1.0.1.dist-info/top_level.txt
colorred_py-1.0.1.dist-info/RECORD
